{"country": "Azerbaijan", "results": [{"feature": "cluster_features", "rows": 91, "waves": ["1995"], "status": "OK", "failed": [], "warned": ["has_household_index"]}, {"feature": "household_characteristics", "rows": 2016, "waves": ["1995"], "status": "OK", "failed": [], "warned": []}, {"feature": "household_roster", "rows": 10012, "waves": ["1995"], "status": "OK", "failed": [], "warned": ["index_levels_match_scheme"]}, {"feature": "housing", "rows": 2016, "waves": ["1995"], "status": "OK", "failed": [], "warned": ["index_levels_match_scheme"]}, {"feature": "individual_education", "rows": 9005, "waves": ["1995"], "status": "OK", "failed": [], "warned": ["index_levels_match_scheme"]}, {"feature": "interview_date", "rows": 2015, "waves": ["1995"], "status": "OK", "failed": [], "warned": ["index_levels_match_scheme"]}, {"feature": "sample", "rows": 2016, "waves": ["1995"], "status": "OK", "failed": [], "warned": []}]}