{"country": "GhanaLSS", "results": [{"feature": "cluster_features", "rows": 2780, "waves": ["2005-06", "2012-13", "2016-17"], "status": "OK", "failed": [], "warned": ["has_household_index"]}, {"feature": "food_acquired", "rows": 1083476, "waves": ["1987-88", "1988-89", "1991-92", "1998-99", "2005-06", "2012-13"], "status": "SANE_FAIL", "failed": ["declared_columns_present"], "warned": ["index_levels_match_scheme", "no_null_index_levels"]}, {"feature": "food_expenditures", "rows": 461602, "waves": ["2012-13"], "status": "OK", "failed": [], "warned": []}, {"feature": "food_prices", "status": "CRASH", "error_type": "RuntimeError", "error": "Could not materialize GhanaLSS/food_prices: no wave-level build succeeded and no cached parquet was found at /global/home/users/ligon/.local/share/lsms_library/GhanaLSS/var/food_prices.parquet.\n\nCommo", "where": ""}, {"feature": "food_quantities", "status": "CRASH", "error_type": "RuntimeError", "error": "Could not materialize GhanaLSS/food_quantities: no wave-level build succeeded and no cached parquet was found at /global/home/users/ligon/.local/share/lsms_library/GhanaLSS/var/food_quantities.parquet", "where": ""}, {"feature": "food_security", "rows": 13892, "waves": ["2016-17"], "status": "SANE_FAIL", "failed": ["no_all_null_columns"], "warned": ["index_levels_match_scheme", "no_constant_columns"]}, {"feature": "household_characteristics", "rows": 56311, "waves": ["1987-88", "1988-89", "1991-92", "1998-99", "2005-06", "2012-13", "2016-17"], "status": "OK", "failed": [], "warned": []}, {"feature": "household_roster", "rows": 246584, "waves": ["1987-88", "1988-89", "1991-92", "1998-99", "2005-06", "2012-13", "2016-17"], "status": "OK", "failed": [], "warned": ["index_levels_match_scheme", "no_constant_columns"]}, {"feature": "housing", "rows": 49994, "waves": ["1991-92", "1998-99", "2005-06", "2012-13", "2016-17"], "status": "OK", "failed": [], "warned": ["index_levels_match_scheme"]}, {"feature": "individual_education", "rows": 95851, "waves": ["1998-99", "2012-13", "2016-17"], "status": "OK", "failed": [], "warned": ["index_levels_match_scheme"]}, {"feature": "interview_date", "rows": 56338, "waves": ["1987-88", "1988-89", "1991-92", "1998-99", "2005-06", "2012-13", "2016-17"], "status": "OK", "failed": [], "warned": ["index_levels_match_scheme"]}, {"feature": "panel_ids", "status": "BUILT_PROPERTY", "n": 714}, {"feature": "plot_features", "rows": 48349, "waves": ["1991-92", "1998-99", "2012-13", "2016-17"], "status": "OK", "failed": [], "warned": ["index_levels_match_scheme"]}, {"feature": "sample", "rows": 56328, "waves": ["1987-88", "1988-89", "1991-92", "1998-99", "2005-06", "2012-13", "2016-17"], "status": "OK", "failed": [], "warned": []}]}